Workbook

Sheet RepublicanUsers
A1: userId | B1: Label | C1: Number | D1: NewId | E1: NewId
A2: 1.7095642e+18 | B2: R | C2: 1 | D2: =_xlfn.CONCAT(B2,C2) -> R1 | E2: R1
A3: 1.4911877e+18 | B3: R | C3: 2 | D3: =_xlfn.CONCAT(B3,C3) -> R2 | E3: R2
A4: 28264000 | B4: R | C4: 3 | D4: =_xlfn.CONCAT(B4,C4) -> R3 | E4: R3
A5: 2921776421 | B5: R | C5: 4 | D5: =_xlfn.CONCAT(B5,C5) -> R4 | E5: R4
A6: 200466783 | B6: R | C6: 5 | D6: =_xlfn.CONCAT(B6,C6) -> R5 | E6: R5
A7: 487800581 | B7: R | C7: 6 | D7: =_xlfn.CONCAT(B7,C7) -> R6 | E7: R6
A8: 1.6895318e+18 | B8: R | C8: 7 | D8: =_xlfn.CONCAT(B8,C8) -> R7 | E8: R7
A9: 1.6079333e+18 | B9: R | C9: 8 | D9: =_xlfn.CONCAT(B9,C9) -> R8 | E9: R8
A10: 17550469 | B10: R | C10: 9 | D10: =_xlfn.CONCAT(B10,C10) -> R9 | E10: R9
A11: 286227273 | B11: R | C11: 10 | D11: =_xlfn.CONCAT(B11,C11) -> R10 | E11: R10
A12: 1.4911877e+18 | B12: R | C12: 11 | D12: =_xlfn.CONCAT(B12,C12) -> R11 | E12: R11
A13: 127914524 | B13: R | C13: 12 | D13: =_xlfn.CONCAT(B13,C13) -> R12 | E13: R12
... A1310: 1.7403971e+18 | B1310: R | C1310: 1309 | D1310: =_xlfn.CONCAT(B1310,C1310) -> R1309 | E1310: R1309

Sheet RepublicanTweets
A1: text | B1: id_str | C1: user | D1: userId | E1: NewUserId
A2: @ianbremmer LOLOLOL. Until the Waffle House opened up. #cmonman #maga https://t.co/h0XCTse1zp | B2: 1813681120162259372 | C2: {'id': 1709564235846422528, 'id_str': '1709564235846422528', 'url': 'https://twitter.com/BonerLord420', 'username': 'BonerLord420', 'rawDescription': '', 'created': datetime.datetime(2023, 10, 4, 13, 41, 2, tzinfo=datetime.timezone.utc), 'followersCount': 229, 'friendsCount': 613, 'statusesCount': 20685, 'favouritesCount': 32189, 'listedCount': 16, 'mediaCount': 2874, 'location': 'Above 5000 Feet', 'profileImageUrl': 'https://pbs.twimg.com/profile_images/1766479985278124032/ECfvZGzS_normal.jpg', 'profileBannerUrl': 'PW', 'protected': 'PW', 'verified': False, 'blue': False, 'blueType': None, 'descriptionLinks': ['PW'], '_type': 'PW'} | D2: =VALUE(MID(C2, SEARCH("{'id':", C2) + 6, SEARCH(", '", C2) - SEARCH("{'id':", C2) - 6)) -> 1.7095642e+18 | E2: =VLOOKUP(Table2[[#This Row],[userId]],RepublicanUsers!$A$1:$E$1310,5,FALSE) -> R1
A3: @mattysoul @SChimamoto #MAGA #FJB IFBAP ðŸ‡ºðŸ‡¸ðŸ¦… https://t.co/bNg6MHLjy4 | B3: 1813681095571099955 | C3: {'id': 1491187724291915777, 'id_str': '1491187724291915777', 'url': 'https://twitter.com/shelby chimamotoðŸ‡ºðŸ‡¸ðŸ¦…', 'username': 'shelby chimamotoðŸ‡ºðŸ‡¸ðŸ¦…', 'rawDescription': 'When they test your Fear, they test your Faith! Live and speak the Truth. Bow only to God! ðŸ‡ºðŸ‡¸ #IFBAP #MAGA #2A ðŸ‡ºðŸ‡¸ðŸ¦…\nKeto/CarnivoreðŸš«DM', 'created': datetime.datetime(2022, 2, 8, 23, 11, 41, tzinfo=datetime.timezone.utc), 'followersCount': 98351, 'friendsCount': 79979, 'statusesCount': 97846, 'favouritesCount': 173933, 'listedCount': 22, 'mediaCount': 25718, 'location': '', 'profileImageUrl': 'https://pbs.twimg.com/profile_images/1491188010234302470/VcEvV6_n_normal.jpg', 'profileBannerUrl': 'PW', 'protected': 'PW', 'verified': False, 'blue': True, 'blueType': None, 'descriptionLinks': ['PW'], '_type': 'PW'} | D3: =VALUE(MID(C3, SEARCH("{'id':", C3) + 6, SEARCH(", '", C3) - SEARCH("{'id':", C3) - 6)) -> 1.4911877e+18 | E3: =VLOOKUP(Table2[[#This Row],[userId]],RepublicanUsers!$A$1:$E$1310,5,FALSE) -> R2
A4: #Trump #TrumpRally #SecretService #Trump2024 #DonaldTrump #MAGA How the Secret Service acted at the Trump Rally: ðŸ¤£ðŸ˜‚ðŸ¤£ðŸ˜‚ðŸ¤£ðŸ˜‚ðŸ¤£ðŸ˜‚ https://t.co/tsSgfYTCH5 | B4: 1813681072930189369 | C4: {'id': 28264000, 'id_str': '28264000', 'url': 'https://twitter.com/Aurora', 'username': 'Aurora', 'rawDescription': 'OPLiveðŸ’™BackTheBlue â¤ God & My family which includes my pets. IT Geek. Twitter is not a dating site ðŸ™‚', 'created': datetime.datetime(2009, 4, 2, 2, 42, 44, tzinfo=datetime.timezone.utc), 'followersCount': 307, 'friendsCount': 972, 'statusesCount': 6859, 'favouritesCount': 15623, 'listedCount': 0, 'mediaCount': 812, 'location': 'USA', 'profileImageUrl': 'https://pbs.twimg.com/profile_images/1803494450062102529/og-CV2_f_normal.jpg', 'profileBannerUrl': 'PW', 'protected': 'PW', 'verified': False, 'blue': False, 'blueType': None, 'descriptionLinks': ['PW'], '_type': 'PW'} | D4: =VALUE(MID(C4, SEARCH("{'id':", C4) + 6, SEARCH(", '", C4) - SEARCH("{'id':", C4) - 6)) -> 28264000 | E4: =VLOOKUP(Table2[[#This Row],[userId]],RepublicanUsers!$A$1:$E$1310,5,FALSE) -> R3
A5: @RealMattCouch Our next President ðŸ™ðŸ»â¤ï¸ðŸ‡ºðŸ‡¸ #MAGA | B5: 1813681067448234045 | C5: {'id': 2921776421, 'id_str': '2921776421', 'url': 'https://twitter.com/Annie', 'username': 'Annie', 'rawDescription': 'America first, Christian ðŸ™ðŸ»â¤ï¸ðŸ‡ºðŸ‡¸', 'created': datetime.datetime(2014, 12, 14, 18, 42, 45, tzinfo=datetime.timezone.utc), 'followersCount': 3687, 'friendsCount': 485, 'statusesCount': 65438, 'favouritesCount': 284942, 'listedCount': 17, 'mediaCount': 55, 'location': '', 'profileImageUrl': 'https://pbs.twimg.com/profile_images/1766568514305859584/goinyvZZ_normal.jpg', 'profileBannerUrl': 'PW', 'protected': 'PW', 'verified': False, 'blue': True, 'blueType': None, 'descriptionLinks': ['PW'], '_type': 'PW'} | D5: =VALUE(MID(C5, SEARCH("{'id':", C5) + 6, SEARCH(", '", C5) - SEARCH("{'id':", C5) - 6)) -> 2921776421 | E5: =VLOOKUP(Table2[[#This Row],[userId]],RepublicanUsers!$A$1:$E$1310,5,FALSE) -> R4
A6: @israelUSAforeve Ok ? And ? Nobody cares. #Trump2024 #MAGA #AmericaFirst | B6: 1813681042525401203 | C6: {'id': 200466783, 'id_str': '200466783', 'url': 'https://twitter.com/Trump2024 MAGA', 'username': 'Trump2024 MAGA', 'rawDescription': 'Just an everyday guy. I use X to entertain myself with your bullshit.', 'created': datetime.datetime(2010, 10, 9, 11, 16, 24, tzinfo=datetime.timezone.utc), 'followersCount': 705, 'friendsCount': 709, 'statusesCount': 20971, 'favouritesCount': 54099, 'listedCount': 5, 'mediaCount': 83, 'location': 'Ohio, USA', 'profileImageUrl': 'https://pbs.twimg.com/profile_images/1812745429840224256/ursqYU5z_normal.jpg', 'profileBannerUrl': 'PW', 'protected': 'PW', 'verified': False, 'blue': True, 'blueType': None, 'descriptionLinks': ['PW'], '_type': 'PW'} | D6: =VALUE(MID(C6, SEARCH("{'id':", C6) + 6, SEARCH(", '", C6) - SEARCH("{'id':", C6) - 6)) -> 200466783 | E6: =VLOOKUP(Table2[[#This Row],[userId]],RepublicanUsers!$A$1:$E$1310,5,FALSE) -> R5
A7: #maga know not to buy teslas ~ they won't run at night because the sun is not out ~ | B7: 1813681006865461564 | C7: {'id': 487800581, 'id_str': '487800581', 'url': 'https://twitter.com/Screaming Butterfly', 'username': 'Screaming Butterfly', 'rawDescription': 'Facts ~ follow me get pissed...\ncry a lot ~ laugh a lot a lot, alot\nWork with veterans, stars, artists and...\nOh yeah filmmaker, author. News films and books', 'created': datetime.datetime(2012, 2, 9, 19, 13, 46, tzinfo=datetime.timezone.utc), 'followersCount': 3180, 'friendsCount': 3555, 'statusesCount': 38767, 'favouritesCount': 2670, 'listedCount': 35, 'mediaCount': 380, 'location': 'Eternal Reoccurence', 'profileImageUrl': 'https://pbs.twimg.com/profile_images/1773150864292667392/KV990k-4_normal.jpg', 'profileBannerUrl': 'PW', 'protected': 'PW', 'verified': False, 'blue': False, 'blueType': None, 'descriptionLinks': ['PW'], '_type': 'PW'} | D7: =VALUE(MID(C7, SEARCH("{'id':", C7) + 6, SEARCH(", '", C7) - SEARCH("{'id':", C7) - 6)) -> 487800581 | E7: =VLOOKUP(Table2[[#This Row],[userId]],RepublicanUsers!$A$1:$E$1310,5,FALSE) -> R6
A8: @TONYxTWO Prayers up to that patriot. He should recover faster. #MAGA | B8: 1813680846077104273 | C8: {'id': 1689531817269870592, 'id_str': '1689531817269870592', 'url': 'https://twitter.com/Gomeez', 'username': 'Gomeez', 'rawDescription': '|Entrepreneur | Investor & Business woman | #MAGA SUPPORTER |Hustler ðŸ | Activist ðŸ‡¹ðŸ‡¿ | Simba sc| Madrid fan| cool & fine girlâ¤ï¸ðŸ¥°ðŸ’‹ |', 'created': datetime.datetime(2023, 8, 10, 6, 59, 33, tzinfo=datetime.timezone.utc), 'followersCount': 2077, 'friendsCount': 3141, 'statusesCount': 5691, 'favouritesCount': 5550, 'listedCount': 0, 'mediaCount': 641, 'location': 'Canada ðŸ , Tanzania ðŸ‡¹ðŸ‡¿', 'profileImageUrl': 'https://pbs.twimg.com/profile_images/1766706342742446080/-Pr-m_wy_normal.jpg', 'profileBannerUrl': 'PW', 'protected': 'PW', 'verified': False, 'blue': False, 'blueType': None, 'descriptionLinks': ['PW'], '_type': 'PW'} | D8: =VALUE(MID(C8, SEARCH("{'id':", C8) + 6, SEARCH(", '", C8) - SEARCH("{'id':", C8) - 6)) -> 1.6895318e+18 | E8: =VLOOKUP(Table2[[#This Row],[userId]],RepublicanUsers!$A$1:$E$1310,5,FALSE) -> R7
A9: @realTuckFrumper Just so you know if Dems in Congress knock him off the Ballot ?? #MAGA is prepared to sue states to have Biden put back on the Ballot. Learn the #Facts people b4 you start spreading this BS. | B9: 1813680828750409993 | C9: {'id': 1607933291474165763, 'id_str': '1607933291474165763', 'url': 'https://twitter.com/Always Vote ðŸ’™ðŸ’™ ðŸ˜‡ðŸ’™Always_Vote 24', 'username': 'Always Vote ðŸ’™ðŸ’™ ðŸ˜‡ðŸ’™Always_Vote 24', 'rawDescription': 'Sports Lover ðŸ€ðŸˆ Determined to get 90% of registered Dems 2 VOTE ðŸ’™in every election. Voice your opinion. V O T E', 'created': datetime.datetime(2022, 12, 28, 2, 56, 47, tzinfo=datetime.timezone.utc), 'followersCount': 3439, 'friendsCount': 5405, 'statusesCount': 22921, 'favouritesCount': 54030, 'listedCount': 7, 'mediaCount': 14102, 'location': 'Philadelphia, PA', 'profileImageUrl': 'https://pbs.twimg.com/profile_images/1687651626083840002/658FmQdo_normal.jpg', 'profileBannerUrl': 'PW', 'protected': 'PW', 'verified': False, 'blue': False, 'blueType': None, 'descriptionLinks': ['PW'], '_type': 'PW'} | D9: =VALUE(MID(C9, SEARCH("{'id':", C9) + 6, SEARCH(", '", C9) - SEARCH("{'id':", C9) - 6)) -> 1.6079333e+18 | E9: =VLOOKUP(Table2[[#This Row],[userId]],RepublicanUsers!$A$1:$E$1310,5,FALSE) -> R8
A10: @LivingInArcata @MayoIsSpicyy We're better off him not explaining since it will only drag out this self-inflicted torture; when the stakes couldn't be higher, we are collectively shotting ourselves in the foot. We're fighting #MAGA &amp; should't be fighting each other. He knows that. So, why woud he do this? | B10: 1813680813034369102 | C10: {'id': 17550469, 'id_str': '17550469', 'url': 'https://twitter.com/Susan M. Furey Ed.D.', 'username': 'Susan M. Furey Ed.D.', 'rawDescription': 'Lifelong educator with focus on education, storytelling, dialogue, leadership, inspired ideas, advocacy for women & social justice. Proud, empathic progressive.', 'created': datetime.datetime(2008, 11, 22, 1, 33, 26, tzinfo=datetime.timezone.utc), 'followersCount': 3846, 'friendsCount': 5012, 'statusesCount': 67559, 'favouritesCount': 29530, 'listedCount': 235, 'mediaCount': 5054, 'location': 'Wynnewood, PA', 'profileImageUrl': 'https://pbs.twimg.com/profile_images/1827796563583803392/hplmvJPz_normal.jpg', 'profileBannerUrl': 'PW', 'protected': 'PW', 'verified': False, 'blue': False, 'blueType': None, 'descriptionLinks': ['PW'], '_type': 'PW'} | D10: =VALUE(MID(C10, SEARCH("{'id':", C10) + 6, SEARCH(", '", C10) - SEARCH("{'id':", C10) - 6)) -> 17550469 | E10: =VLOOKUP(Table2[[#This Row],[userId]],RepublicanUsers!$A$1:$E$1310,5,FALSE) -> R9
A11: @LupusWarrior69 @GOP #magaIsATerroristOrg and must be stopped by voting #BidenHarris2024ToProtectDemocracy | B11: 1813680764120150090 | C11: {'id': 286227273, 'id_str': '286227273', 'url': 'https://twitter.com/@sergiodomeyko@mastodon.online ðŸ‡ºðŸ‡¸ðŸ‡¨ðŸ‡±ðŸ‡ºðŸ‡¦', 'username': '@sergiodomeyko@mastodon.online ðŸ‡ºðŸ‡¸ðŸ‡¨ðŸ‡±ðŸ‡ºðŸ‡¦', 'rawDescription': 'Silicon Valley transplant living in Chile. Trail running adventures, green tech, ðŸ‡ºðŸ‡¸USCG Veteran. Find me on Mastodon: https://t.co/VXb7h9Xje4 ðŸŒ', 'created': datetime.datetime(2011, 4, 22, 15, 54, 51, tzinfo=datetime.timezone.utc), 'followersCount': 2862, 'friendsCount': 2695, 'statusesCount': 43294, 'favouritesCount': 119195, 'listedCount': 12, 'mediaCount': 4401, 'location': 'California/Chicureo, Chile', 'profileImageUrl': 'https://pbs.twimg.com/profile_images/1708250293765337088/8PpiIqmL_normal.jpg', 'profileBannerUrl': 'PW', 'protected': 'PW', 'verified': False, 'blue': False, 'blueType': None, 'descriptionLinks': ['PW'], '_type': 'PW'} | D11: =VALUE(MID(C11, SEARCH("{'id':", C11) + 6, SEARCH(", '", C11) - SEARCH("{'id':", C11) - 6)) -> 286227273 | E11: =VLOOKUP(Table2[[#This Row],[userId]],RepublicanUsers!$A$1:$E$1310,5,FALSE) -> R10
A12: @Thapz__ @SChimamoto #MAGA #FJB IFBAP ðŸ‡ºðŸ‡¸ðŸ¦… | B12: 1813680751629713811 | C12: {'id': 1491187724291915777, 'id_str': '1491187724291915777', 'url': 'https://twitter.com/shelby chimamotoðŸ‡ºðŸ‡¸ðŸ¦…', 'username': 'shelby chimamotoðŸ‡ºðŸ‡¸ðŸ¦…', 'rawDescription': 'When they test your Fear, they test your Faith! Live and speak the Truth. Bow only to God! ðŸ‡ºðŸ‡¸ #IFBAP #MAGA #2A ðŸ‡ºðŸ‡¸ðŸ¦…\nKeto/CarnivoreðŸš«DM', 'created': datetime.datetime(2022, 2, 8, 23, 11, 41, tzinfo=datetime.timezone.utc), 'followersCount': 98357, 'friendsCount': 79979, 'statusesCount': 97846, 'favouritesCount': 173933, 'listedCount': 22, 'mediaCount': 25718, 'location': '', 'profileImageUrl': 'https://pbs.twimg.com/profile_images/1491188010234302470/VcEvV6_n_normal.jpg', 'profileBannerUrl': 'PW', 'protected': 'PW', 'verified': False, 'blue': True, 'blueType': None, 'descriptionLinks': ['PW'], '_type': 'PW'} | D12: =VALUE(MID(C12, SEARCH("{'id':", C12) + 6, SEARCH(", '", C12) - SEARCH("{'id':", C12) - 6)) -> 1.4911877e+18 | E12: =VLOOKUP(Table2[[#This Row],[userId]],RepublicanUsers!$A$1:$E$1310,5,FALSE) -> R2
A13: Treason! They knew before POTUS Trump even got on stage... ðŸ¤¬ #MAGA | B13: 1813680723053985942 | C13: {'id': 127914524, 'id_str': '127914524', 'url': "https://twitter.com/Let's try LOGIC", 'username': "Let's try LOGIC", 'rawDescription': 'ðŸ‡ºðŸ‡¸ðŸ¿ #MAGA #MAHA mixed in with some Aloha! ðŸ¤™ðŸ½ ðŸ‡ºðŸ‡¸IFBAPðŸ‡ºðŸ‡¸', 'created': datetime.datetime(2010, 3, 30, 16, 17, 37, tzinfo=datetime.timezone.utc), 'followersCount': 2363, 'friendsCount': 3165, 'statusesCount': 13895, 'favouritesCount': 20524, 'listedCount': 1, 'mediaCount': 535, 'location': '', 'profileImageUrl': 'https://pbs.twimg.com/profile_images/1129083529/socrates___plato_normal.jpg', 'profileBannerUrl': 'PW', 'protected': 'PW', 'verified': False, 'blue': True, 'blueType': None, 'descriptionLinks': ['PW'], '_type': 'PW'} | D13: =VALUE(MID(C13, SEARCH("{'id':", C13) + 6, SEARCH(", '", C13) - SEARCH("{'id':", C13) - 6)) -> 127914524 | E13: =VLOOKUP(Table2[[#This Row],[userId]],RepublicanUsers!$A$1:$E$1310,5,FALSE) -> R12
... A1310: #FactCheck #BIDEN #AmericaFirst #January6th #TrumpAssasinationAttempt @SpeakerPelosi @JoeBiden @realDonaldTrump https://t.co/WSYLZcOjMU | B1310: 1813661149814280544 | C1310: {'id': 1740397052775841792, 'id_str': '1740397052775841792', 'url': 'https://twitter.com/Taylor', 'username': 'Taylor', 'rawDescription': 'God & America first, proud straight man, keep tax dollars local, term limits, & love who you want, leave the kids out of it.\nSaints ðŸˆ , ðŸš´ðŸ»\nðŸ‘‰ðŸ¼ðŸš«DMâ€™sðŸ‘ˆðŸ½', 'created': datetime.datetime(2023, 12, 28, 15, 40, 24, tzinfo=datetime.timezone.utc), 'followersCount': 1109, 'friendsCount': 1690, 'statusesCount': 706, 'favouritesCount': 8659, 'listedCount': 0, 'mediaCount': 226, 'location': 'Louisiana / Texas / California', 'profileImageUrl': 'https://pbs.twimg.com/profile_images/1801695218791546880/_K9u0dOo_normal.jpg', 'profileBannerUrl': 'PW', 'protected': 'PW', 'verified': False, 'blue': False, 'blueType': None, 'descriptionLinks': ['PW'], '_type': 'PW'} | D1310: =VALUE(MID(C1310, SEARCH("{'id':", C1310) + 6, SEARCH(", '", C1310) - SEARCH("{'id':", C1310) - 6)) -> 1.7403971e+18 | E1310: =VLOOKUP(Table2[[#This Row],[userId]],RepublicanUsers!$A$1:$E$1310,5,FALSE) -> R1309

Sheet DemocratUsers
A1: userId | B1: Label | C1: Number | D1: NewId | E1: NewId
A2: 2348543166 | B2: D | C2: 1 | D2: =_xlfn.CONCAT(B2,C2) -> D1 | E2: D1
A3: 9.0804414e+17 | B3: D | C3: 2 | D3: =_xlfn.CONCAT(B3,C3) -> D2 | E3: D2
A4: 1.1756104e+18 | B4: D | C4: 3 | D4: =_xlfn.CONCAT(B4,C4) -> D3 | E4: D3
A5: 286227273 | B5: D | C5: 4 | D5: =_xlfn.CONCAT(B5,C5) -> D4 | E5: D4
A6: 1.6429044e+18 | B6: D | C6: 5 | D6: =_xlfn.CONCAT(B6,C6) -> D5 | E6: D5
A7: 1.7092414e+18 | B7: D | C7: 6 | D7: =_xlfn.CONCAT(B7,C7) -> D6 | E7: D6
A8: 275783771 | B8: D | C8: 7 | D8: =_xlfn.CONCAT(B8,C8) -> D7 | E8: D7
A9: 2433092624 | B9: D | C9: 8 | D9: =_xlfn.CONCAT(B9,C9) -> D8 | E9: D8
A10: 1.2218726e+18 | B10: D | C10: 9 | D10: =_xlfn.CONCAT(B10,C10) -> D9 | E10: D9
A11: 1.3077954e+18 | B11: D | C11: 10 | D11: =_xlfn.CONCAT(B11,C11) -> D10 | E11: D10
A12: 570121611 | B12: D | C12: 11 | D12: =_xlfn.CONCAT(B12,C12) -> D11 | E12: D11
A13: 1.3073906e+18 | B13: D | C13: 12 | D13: =_xlfn.CONCAT(B13,C13) -> D12 | E13: D12
... A427: 312256506 | B427: D | C427: 426 | D427: =_xlfn.CONCAT(B427,C427) -> D426 | E427: D426

Sheet DemocratTweets
A1: text | B1: id_str | C1: user | D1: userId | E1: newUserId
A2: @RepJeffries yeah well as long as you won't come out and support #BidenHarris2024 100% we will see #project2025 starting jan 20 2025. get your act together dems and start supporting biden. | B2: 1813681121638625622 | C2: {'id': 2348543166, 'id_str': '2348543166', 'url': 'https://twitter.com/just gina ðŸ‘» \uea00 ðŸ¥¥ ðŸŒ´', 'username': 'just gina ðŸ‘» \uea00 ðŸ¥¥ ðŸŒ´', 'rawDescription': 'To a mantis shrimp, kung fu looks like taichi. --ZeFrank. \ncalifornia, ucla, film, sociology, nanowrimo\nbe kind\nblah blah woof woof', 'created': datetime.datetime(2014, 2, 17, 14, 14, 1, tzinfo=datetime.timezone.utc), 'followersCount': 1639, 'friendsCount': 3832, 'statusesCount': 19256, 'favouritesCount': 57546, 'listedCount': 0, 'mediaCount': 1219, 'location': '', 'profileImageUrl': 'https://pbs.twimg.com/profile_images/1360656649115947009/MGO3A_2w_normal.jpg', 'profileBannerUrl': 'PW', 'protected': 'PW', 'verified': False, 'blue': False, 'blueType': None, 'descriptionLinks': ['PW'], '_type': 'PW'} | D2: =VALUE(MID(C2, SEARCH("{'id':", C2) + 6, SEARCH(", '", C2) - SEARCH("{'id':", C2) - 6)) -> 2348543166 | E2: =VLOOKUP(Table1[[#This Row],[userId]],DemocratUsers!$A$1:$E$427,5,FALSE) -> D1
A3: @TeamTrumpâ€” the Democratic Presidential nominee will be Joe Biden and the Vice Presidential nominee will be Kamala Harris. Seems like someone is scared of the VP and canâ€™t handle the heat. #BidenHarris2024 https://t.co/R5XQLJy78M | B3: 1813681094530838995 | C3: {'id': 908044138146385920, 'id_str': '908044138146385920', 'url': 'https://twitter.com/Democratic Politics', 'username': 'Democratic Politics', 'rawDescription': 'Together, united, as one country we can be a force for change. - Vice President Kamala Harris #HarrisWalz2024 ðŸ‡ºðŸ‡¸ #BlackLivesMatter', 'created': datetime.datetime(2017, 9, 13, 19, 6, 7, tzinfo=datetime.timezone.utc), 'followersCount': 190, 'friendsCount': 240, 'statusesCount': 14094, 'favouritesCount': 26004, 'listedCount': 1, 'mediaCount': 1861, 'location': '', 'profileImageUrl': 'https://pbs.twimg.com/profile_images/1840179739979313152/mzbLCnja_normal.jpg', 'profileBannerUrl': 'PW', 'protected': 'PW', 'verified': False, 'blue': False, 'blueType': None, 'descriptionLinks': ['PW'], '_type': 'PW'} | D3: =VALUE(MID(C3, SEARCH("{'id':", C3) + 6, SEARCH(", '", C3) - SEARCH("{'id':", C3) - 6)) -> 9.0804414e+17 | E3: =VLOOKUP(Table1[[#This Row],[userId]],DemocratUsers!$A$1:$E$427,5,FALSE) -> D2
A4: @loveeducationjs @elonmusk Joe Biden did all of that. It didn't happen on its own. #BidenHarris2024 | B4: 1813680861138575688 | C4: {'id': 1175610389771497472, 'id_str': '1175610389771497472', 'url': 'https://twitter.com/Cindy Takaht', 'username': 'Cindy Takaht', 'rawDescription': 'We must all be on the path to being our best selves.', 'created': datetime.datetime(2019, 9, 22, 3, 19, 11, tzinfo=datetime.timezone.utc), 'followersCount': 5574, 'friendsCount': 7498, 'statusesCount': 208871, 'favouritesCount': 139774, 'listedCount': 8, 'mediaCount': 288, 'location': 'Reality', 'profileImageUrl': 'https://pbs.twimg.com/profile_images/1175610707427115013/azIVAVjv_normal.jpg', 'profileBannerUrl': 'PW', 'protected': 'PW', 'verified': False, 'blue': False, 'blueType': None, 'descriptionLinks': ['PW'], '_type': 'PW'} | D4: =VALUE(MID(C4, SEARCH("{'id':", C4) + 6, SEARCH(", '", C4) - SEARCH("{'id':", C4) - 6)) -> 1.1756104e+18 | E4: =VLOOKUP(Table1[[#This Row],[userId]],DemocratUsers!$A$1:$E$427,5,FALSE) -> D3
A5: @LupusWarrior69 @GOP #magaIsATerroristOrg and must be stopped by voting #BidenHarris2024ToProtectDemocracy | B5: 1813680764120150090 | C5: {'id': 286227273, 'id_str': '286227273', 'url': 'https://twitter.com/@sergiodomeyko@mastodon.online ðŸ‡ºðŸ‡¸ðŸ‡¨ðŸ‡±ðŸ‡ºðŸ‡¦', 'username': '@sergiodomeyko@mastodon.online ðŸ‡ºðŸ‡¸ðŸ‡¨ðŸ‡±ðŸ‡ºðŸ‡¦', 'rawDescription': 'Silicon Valley transplant living in Chile. Trail running adventures, green tech, ðŸ‡ºðŸ‡¸USCG Veteran. Find me on Mastodon: https://t.co/VXb7h9Xje4 ðŸŒ', 'created': datetime.datetime(2011, 4, 22, 15, 54, 51, tzinfo=datetime.timezone.utc), 'followersCount': 2862, 'friendsCount': 2695, 'statusesCount': 43294, 'favouritesCount': 119195, 'listedCount': 12, 'mediaCount': 4401, 'location': 'California/Chicureo, Chile', 'profileImageUrl': 'https://pbs.twimg.com/profile_images/1708250293765337088/8PpiIqmL_normal.jpg', 'profileBannerUrl': 'PW', 'protected': 'PW', 'verified': False, 'blue': False, 'blueType': None, 'descriptionLinks': ['PW'], '_type': 'PW'} | D5: =VALUE(MID(C5, SEARCH("{'id':", C5) + 6, SEARCH(", '", C5) - SEARCH("{'id':", C5) - 6)) -> 286227273 | E5: =VLOOKUP(Table1[[#This Row],[userId]],DemocratUsers!$A$1:$E$427,5,FALSE) -> D4
A6: President Trump got you down? #Biden2024 #BidenHarris2024 #Trump #Trump2024 #TrumpVance2024 https://t.co/0Xo1Msgb4Y | B6: 1813680522524328041 | C6: {'id': 1642904375831015426, 'id_str': '1642904375831015426', 'url': 'https://twitter.com/No one you knowâ€¦yet', 'username': 'No one you knowâ€¦yet', 'rawDescription': 'Nothing to see here, Iâ€™m here for my own amusement. keep scrolling.', 'created': datetime.datetime(2023, 4, 3, 14, 58, 41, tzinfo=datetime.timezone.utc), 'followersCount': 47, 'friendsCount': 82, 'statusesCount': 10416, 'favouritesCount': 15, 'listedCount': 1, 'mediaCount': 3428, 'location': 'Tampa, FL', 'profileImageUrl': 'https://pbs.twimg.com/profile_images/1712628641517953024/UnGGROAi_normal.jpg', 'profileBannerUrl': 'PW', 'protected': 'PW', 'verified': False, 'blue': False, 'blueType': None, 'descriptionLinks': ['PW'], '_type': 'PW'} | D6: =VALUE(MID(C6, SEARCH("{'id':", C6) + 6, SEARCH(", '", C6) - SEARCH("{'id':", C6) - 6)) -> 1.6429044e+18 | E6: =VLOOKUP(Table1[[#This Row],[userId]],DemocratUsers!$A$1:$E$427,5,FALSE) -> D5
A7: Dear @hakeemjeffries @RepJeffries @AdamSchiff @RepAdamSchiff @SenSchumer @RepRaskin @jamie_raskin all you're accomplishing with your "Biden should drop out" BS is passing off your own voters. Keep going against what #WeThePeople want &amp; see where that gets you. #BidenHarris2024 | B7: 1813680446519255286 | C7: {'id': 1709241425462972416, 'id_str': '1709241425462972416', 'url': 'https://twitter.com/KamKam2023', 'username': 'KamKam2023', 'rawDescription': '', 'created': datetime.datetime(2023, 10, 3, 16, 18, 26, tzinfo=datetime.timezone.utc), 'followersCount': 716, 'friendsCount': 991, 'statusesCount': 30278, 'favouritesCount': 46282, 'listedCount': 1, 'mediaCount': 1704, 'location': '', 'profileImageUrl': 'https://pbs.twimg.com/profile_images/1709241895929737217/piHGkXOz_normal.jpg', 'profileBannerUrl': 'PW', 'protected': 'PW', 'verified': False, 'blue': False, 'blueType': None, 'descriptionLinks': ['PW'], '_type': 'PW'} | D7: =VALUE(MID(C7, SEARCH("{'id':", C7) + 6, SEARCH(", '", C7) - SEARCH("{'id':", C7) - 6)) -> 1.7092414e+18 | E7: =VLOOKUP(Table1[[#This Row],[userId]],DemocratUsers!$A$1:$E$427,5,FALSE) -> D6
A8: To Mr Owen Prague.This pic was 4 years ago when I had cut my own long hair &amp; it was a disaster. But short hair, long hair or bald (hopefully not) I am the same girl that supports Democracy &amp; want to support @POTUS Joe Biden this November. #Biden2024 #BidenHarris2024 | B8: 1813680316688846848 | C8: {'id': 275783771, 'id_str': '275783771', 'url': 'https://twitter.com/LLeigh_Laura ðŸŒ€ ðŸŒŠ', 'username': 'LLeigh_Laura ðŸŒ€ ðŸŒŠ', 'rawDescription': 'Proud Democrat.Instagram @flygirl_ny. Foll by @adamlevine @JohnFugelsang @johnpavlovitz @adamparkhomenko @funder @PalmerReport @davidmweissman @joncoopertweets', 'created': datetime.datetime(2011, 4, 2, 0, 31, 37, tzinfo=datetime.timezone.utc), 'followersCount': 8372, 'friendsCount': 8583, 'statusesCount': 54426, 'favouritesCount': 89084, 'listedCount': 33, 'mediaCount': 1834, 'location': 'New York City, NY', 'profileImageUrl': 'https://pbs.twimg.com/profile_images/1795257527287861248/YrFXLNUb_normal.jpg', 'profileBannerUrl': 'PW', 'protected': 'PW', 'verified': False, 'blue': False, 'blueType': None, 'descriptionLinks': ['PW'], '_type': 'PW'} | D8: =VALUE(MID(C8, SEARCH("{'id':", C8) + 6, SEARCH(", '", C8) - SEARCH("{'id':", C8) - 6)) -> 275783771 | E8: =VLOOKUP(Table1[[#This Row],[userId]],DemocratUsers!$A$1:$E$427,5,FALSE) -> D7
A9: @BGThompsonMS #BidenHarrisToSaveDemocracy #Biden2024 #BidenHarris2024 | B9: 1813680291573325955 | C9: {'id': 2433092624, 'id_str': '2433092624', 'url': 'https://twitter.com/Lisa â˜®ï¸ðŸ’™ðŸ‡ºðŸ‡¸ðŸ¦…', 'username': 'Lisa â˜®ï¸ðŸ’™ðŸ‡ºðŸ‡¸ðŸ¦…', 'rawDescription': 'Free to be meâœŒï¸ðŸ’— Mom of 2. â­ï¸ðŸ’™Pres BidenðŸ! Harris/Walz 24! Cat Lady ðŸ˜» F*â‚¬k MAGAâ€™sðŸ’¥STL Blues Fan ðŸ’ðŸ’™ðŸ’›ðŸ’™ðŸ’ Breast Cancer Survivor ðŸŒ¸#Resist #BLM', 'created': datetime.datetime(2014, 4, 8, 5, 23, 57, tzinfo=datetime.timezone.utc), 'followersCount': 4837, 'friendsCount': 5146, 'statusesCount': 14320, 'favouritesCount': 83646, 'listedCount': 7, 'mediaCount': 913, 'location': '', 'profileImageUrl': 'https://pbs.twimg.com/profile_images/1832900621902508032/RL9iVDPI_normal.jpg', 'profileBannerUrl': 'PW', 'protected': 'PW', 'verified': False, 'blue': False, 'blueType': None, 'descriptionLinks': ['PW'], '_type': 'PW'} | D9: =VALUE(MID(C9, SEARCH("{'id':", C9) + 6, SEARCH(", '", C9) - SEARCH("{'id':", C9) - 6)) -> 2433092624 | E9: =VLOOKUP(Table1[[#This Row],[userId]],DemocratUsers!$A$1:$E$427,5,FALSE) -> D8
A10: @RepAdamSchiff Support Biden now. Iâ€™m sick of this disunity. People like you will be the reason Trump gets elected. You are hurting every day Democrat voters. #BidenHarris2024 | B10: 1813680062656549126 | C10: {'id': 1221872649581797379, 'id_str': '1221872649581797379', 'url': 'https://twitter.com/PA Bloom', 'username': 'PA Bloom', 'rawDescription': 'Harris 2024. ðŸ‡ºðŸ‡¦', 'created': datetime.datetime(2020, 1, 27, 19, 8, 47, tzinfo=datetime.timezone.utc), 'followersCount': 1788, 'friendsCount': 2080, 'statusesCount': 29050, 'favouritesCount': 403437, 'listedCount': 6, 'mediaCount': 108, 'location': 'Pennsylvania, USA', 'profileImageUrl': 'https://pbs.twimg.com/profile_images/1513188276504518659/Hjjzyk8K_normal.jpg', 'profileBannerUrl': 'PW', 'protected': 'PW', 'verified': False, 'blue': False, 'blueType': None, 'descriptionLinks': ['PW'], '_type': 'PW'} | D10: =VALUE(MID(C10, SEARCH("{'id':", C10) + 6, SEARCH(", '", C10) - SEARCH("{'id':", C10) - 6)) -> 1.2218726e+18 | E10: =VLOOKUP(Table1[[#This Row],[userId]],DemocratUsers!$A$1:$E$427,5,FALSE) -> D9
A11: @mmpadellan #Biden2024 #BidenHarris2024 #ThankYouPresidentBiden https://t.co/xGU6mSMv5R | B11: 1813679927725613136 | C11: {'id': 1307795409708953601, 'id_str': '1307795409708953601', 'url': 'https://twitter.com/Nanci@Nanci', 'username': 'Nanci@Nanci', 'rawDescription': '#Dem ðŸŒŠ #SlavaUkraine ðŸ‡ºðŸ‡¦ðŸ’™ðŸ’›ðŸŒ»ðŸ™ðŸ•Šï¸ #UkraineDefendersOfTheFreeWorld #ThankYouUkraine ðŸ‡ºðŸ‡¦ #HarrisWalz2024 #ThankYouPresidentBiden', 'created': datetime.datetime(2020, 9, 20, 21, 35, 19, tzinfo=datetime.timezone.utc), 'followersCount': 988, 'friendsCount': 1103, 'statusesCount': 38161, 'favouritesCount': 200495, 'listedCount': 7, 'mediaCount': 15908, 'location': '', 'profileImageUrl': 'https://pbs.twimg.com/profile_images/1694770532430864384/3Zh10ZXq_normal.jpg', 'profileBannerUrl': 'PW', 'protected': 'PW', 'verified': False, 'blue': True, 'blueType': None, 'descriptionLinks': ['PW'], '_type': 'PW'} | D11: =VALUE(MID(C11, SEARCH("{'id':", C11) + 6, SEARCH(", '", C11) - SEARCH("{'id':", C11) - 6)) -> 1.3077954e+18 | E11: =VLOOKUP(Table1[[#This Row],[userId]],DemocratUsers!$A$1:$E$427,5,FALSE) -> D10
A12: Whatâ€™s the overlap with those whoâ€™ve been demanding his removal over the war crimes being committed by Netanyahu and Israel and who think President Biden can just snap his fingers and end the war? #UniteBlue #VoteBlue #BidenHarris2024 | B12: 1813679890543366478 | C12: {'id': 570121611, 'id_str': '570121611', 'url': 'https://twitter.com/Ken Warnock', 'username': 'Ken Warnock', 'rawDescription': 'Friend, educator, #Guncle #LGBT and #HIV activist, health care management and consultant. Working to make a difference. ðŸ³ï¸\u200dðŸŒˆðŸ³ï¸\u200dâš§ï¸ðŸ³ï¸\u200dðŸŒˆðŸ˜·ðŸ’‰ðŸ’‰ðŸ’‰ðŸ’‰', 'created': datetime.datetime(2012, 5, 3, 15, 0, 42, tzinfo=datetime.timezone.utc), 'followersCount': 2644, 'friendsCount': 1633, 'statusesCount': 371286, 'favouritesCount': 261543, 'listedCount': 176, 'mediaCount': 1705, 'location': 'Royal Oak, Michigan', 'profileImageUrl': 'https://pbs.twimg.com/profile_images/701483345671286784/kWVkw1VV_normal.jpg', 'profileBannerUrl': 'PW', 'protected': 'PW', 'verified': False, 'blue': False, 'blueType': None, 'descriptionLinks': ['PW'], '_type': 'PW'} | D12: =VALUE(MID(C12, SEARCH("{'id':", C12) + 6, SEARCH(", '", C12) - SEARCH("{'id':", C12) - 6)) -> 570121611 | E12: =VLOOKUP(Table1[[#This Row],[userId]],DemocratUsers!$A$1:$E$427,5,FALSE) -> D11
A13: Democrats should unite in support of Biden, who has been the most successful President since Franklin Delano Roosevelt. #BidenHarris2024 #BidenIsAGreatPresident | B13: 1813679622522905011 | C13: {'id': 1307390559301120014, 'id_str': '1307390559301120014', 'url': 'https://twitter.com/BjÃ¶rn-Michael Lange', 'username': 'BjÃ¶rn-Michael Lange', 'rawDescription': 'Rechtsanwalt | Partner @vylegal | Transatlantiker @dajv_ev @DIGeV_de ðŸ‡ºðŸ‡¸ðŸ‡ºðŸ‡¦ðŸ‡ªðŸ‡ºðŸ‡©ðŸ‡ªðŸ‡®ðŸ‡±', 'created': datetime.datetime(2020, 9, 19, 18, 46, 32, tzinfo=datetime.timezone.utc), 'followersCount': 2463, 'friendsCount': 605, 'statusesCount': 4113, 'favouritesCount': 31942, 'listedCount': 15, 'mediaCount': 63, 'location': 'Berlin, Germany', 'profileImageUrl': 'https://pbs.twimg.com/profile_images/1449714438131621888/Z4gc3LE0_normal.jpg', 'profileBannerUrl': 'PW', 'protected': 'PW', 'verified': False, 'blue': True, 'blueType': None, 'descriptionLinks': ['PW'], '_type': 'PW'} | D13: =VALUE(MID(C13, SEARCH("{'id':", C13) + 6, SEARCH(", '", C13) - SEARCH("{'id':", C13) - 6)) -> 1.3073906e+18 | E13: =VLOOKUP(Table1[[#This Row],[userId]],DemocratUsers!$A$1:$E$427,5,FALSE) -> D12
... A427: The Telegraph on "Ukraine The Latest", 7/17/2024, reports that if Trump and Vance are elected in November the US will pull out of NATO. #VoteBlueAsifYourLivesDependonit | B427: 1813658564545929368 | C427: {'id': 312256506, 'id_str': '312256506', 'url': 'https://twitter.com/#GoodTrouble ðŸš« DMs ðŸ‡ºðŸ‡¦ ðŸš«MAGA Kool-Aid Drinkers', 'username': '#GoodTrouble ðŸš« DMs ðŸ‡ºðŸ‡¦ ðŸš«MAGA Kool-Aid Drinkers', 'rawDescription': 'John 14:6: Jesus told him, I am the way, the truth, and the life. No one can come to the Father except through me.â€œTo ignore evil is to be accomplice to itâ€ MLK', 'created': datetime.datetime(2011, 6, 6, 20, 43, 39, tzinfo=datetime.timezone.utc), 'followersCount': 4813, 'friendsCount': 4838, 'statusesCount': 26361, 'favouritesCount': 29806, 'listedCount': 3, 'mediaCount': 884, 'location': 'Pittsburgh, PA', 'profileImageUrl': 'https://pbs.twimg.com/profile_images/1776696210994155520/O-7bw66r_normal.jpg', 'profileBannerUrl': 'PW', 'protected': 'PW', 'verified': False, 'blue': False, 'blueType': None, 'descriptionLinks': ['PW'], '_type': 'PW'} | D427: =VALUE(MID(C427, SEARCH("{'id':", C427) + 6, SEARCH(", '", C427) - SEARCH("{'id':", C427) - 6)) -> 312256506 | E427: =VLOOKUP(Table1[[#This Row],[userId]],DemocratUsers!$A$1:$E$427,5,FALSE) -> D426
